time_server.py
mcp_cuc_syq-0.1.1.dist-info/entry_points.txt
mcp_cuc_syq-0.1.1.dist-info/METADATA
mcp_cuc_syq-0.1.1.dist-info/WHEEL
mcp_cuc_syq-0.1.1.dist-info/RECORD
